sshFRIEND/__init__.py
sshFRIEND/device_types.py
sshFRIEND/ssh_connector.py
sshFRIEND-0.0.11.dist-info/LICENSE
sshFRIEND-0.0.11.dist-info/METADATA
sshFRIEND-0.0.11.dist-info/WHEEL
sshFRIEND-0.0.11.dist-info/top_level.txt
sshFRIEND-0.0.11.dist-info/RECORD
